{"v":"5.6.5","fr":30,"ip":0,"op":56,"w":174,"h":110,"nm":"合成 3","ddd":0,"assets":[{"id":"image_0","w":542,"h":340,"u":"images/","p":"img_sweep_share.png","e":0}],"layers":[{"ddd":0,"ind":1,"ty":2,"nm":"编组 3备份 3.png","cl":"png","refId":"image_0","sr":1,"ks":{"o":{"a":0,"k":100,"ix":11},"r":{"a":0,"k":0,"ix":10},"p":{"a":0,"k":[87,55,0],"ix":2},"a":{"a":0,"k":[271,170,0],"ix":1},"s":{"a":0,"k":[24,24,100],"ix":6}},"ao":0,"hasMask":true,"masksProperties":[{"inv":false,"mode":"a","pt":{"a":1,"k":[{"i":{"x":0.833,"y":0.833},"o":{"x":0.167,"y":0.167},"t":0,"s":[{"i":[[0,0],[0,0],[0,0],[0,0]],"o":[[0,0],[0,0],[0,0],[0,0]],"v":[[351.208,-50.833],[269.958,-50.833],[269.958,399.167],[351.208,399.167]],"c":true}]},{"t":33,"s":[{"i":[[0,0],[0,0],[0,0],[0,0]],"o":[[0,0],[0,0],[0,0],[0,0]],"v":[[613.709,-49.792],[532.459,-49.792],[532.459,400.208],[613.709,400.208]],"c":true}]}],"ix":1},"o":{"a":0,"k":100,"ix":3},"x":{"a":0,"k":0,"ix":4},"nm":"蒙版 1"},{"inv":false,"mode":"a","pt":{"a":1,"k":[{"i":{"x":0.833,"y":0.833},"o":{"x":0.167,"y":0.167},"t":0,"s":[{"i":[[0,0],[0,0],[0,0],[0,0]],"o":[[0,0],[0,0],[0,0],[0,0]],"v":[[268.917,-63.333],[199.125,-63.333],[199.125,456.458],[268.917,456.458]],"c":true}]},{"t":33,"s":[{"i":[[0,0],[0,0],[0,0],[0,0]],"o":[[0,0],[0,0],[0,0],[0,0]],"v":[[2.25,-65.417],[-67.542,-65.417],[-67.542,454.375],[2.25,454.375]],"c":true}]}],"ix":1},"o":{"a":0,"k":100,"ix":3},"x":{"a":0,"k":0,"ix":4},"nm":"蒙版 2"}],"ef":[{"ty":5,"nm":"曲线","np":4,"mn":"ADBE CurvesCustom","ix":1,"en":1,"ef":[{"ty":7,"nm":"通道:","mn":"ADBE CurvesCustom-0002","ix":1,"v":{"a":0,"k":1,"ix":1}},{}]}],"ip":0,"op":900,"st":0,"bm":0},{"ddd":0,"ind":2,"ty":2,"nm":"编组 3备份 3.png","cl":"png","refId":"image_0","sr":1,"ks":{"o":{"a":0,"k":100,"ix":11},"r":{"a":0,"k":0,"ix":10},"p":{"a":0,"k":[87,55,0],"ix":2},"a":{"a":0,"k":[271,170,0],"ix":1},"s":{"a":0,"k":[24,24,100],"ix":6}},"ao":0,"ip":0,"op":900,"st":0,"bm":0}],"markers":[]}